amsdal_integrations/__about__.py
amsdal_integrations/__init__.py
amsdal_integrations/core.py
amsdal_integrations/data_classes.py
amsdal_integrations/py.typed
amsdal_integrations/utils.py
amsdal_integrations/clients/__init__.py
amsdal_integrations/clients/agent_client.py
amsdal_integrations/clients/amsdal_client.py
amsdal_integrations/clients/base.py
amsdal_integrations-0.0.5.dist-info/METADATA
amsdal_integrations-0.0.5.dist-info/WHEEL
amsdal_integrations-0.0.5.dist-info/licenses/LICENSE.txt
amsdal_integrations-0.0.5.dist-info/RECORD
