Metadata-Version: 2.1
Name: amsdal_integrations
Version: 0.0.5
Summary: AMSDAL Integrations - tools that allow integration to various ORM libraries to collect and send data to the AMSDAL application
Project-URL: Documentation, https://pypi.org/project/amsdal_integrations/#readme
Project-URL: Issues, https://github.com/amsdal/amsdal_integrations/issues
Project-URL: Source, https://github.com/amsdal/amsdal_integrations
License: AMSDAL End User License Agreement
License-File: LICENSE.txt
Classifier: Development Status :: 4 - Beta
Classifier: Programming Language :: Python
Classifier: Programming Language :: Python :: 3.7
Classifier: Programming Language :: Python :: 3.8
Classifier: Programming Language :: Python :: 3.9
Classifier: Programming Language :: Python :: 3.10
Classifier: Programming Language :: Python :: 3.11
Classifier: Programming Language :: Python :: Implementation :: CPython
Classifier: Programming Language :: Python :: Implementation :: PyPy
Requires-Python: >=3.7
Requires-Dist: httpx>=0.25.2
